haptik_helpers/__init__.py
haptik_helpers/integrations.py
haptik_helpers/math_ops.py
haptik_helpers-0.1.1.dist-info/METADATA
haptik_helpers-0.1.1.dist-info/WHEEL
haptik_helpers-0.1.1.dist-info/top_level.txt
haptik_helpers-0.1.1.dist-info/RECORD
